schemainspect_idempotent/__init__.py
schemainspect_idempotent/command.py
schemainspect_idempotent/get.py
schemainspect_idempotent/graphlib/__init__.py
schemainspect_idempotent/inspected.py
schemainspect_idempotent/inspector.py
schemainspect_idempotent/misc.py
schemainspect_idempotent/pg/__init__.py
schemainspect_idempotent/pg/obj.py
schemainspect_idempotent/pg/sql/collations.sql
schemainspect_idempotent/pg/sql/collations9.sql
schemainspect_idempotent/pg/sql/constraints.sql
schemainspect_idempotent/pg/sql/deps.sql
schemainspect_idempotent/pg/sql/domains.sql
schemainspect_idempotent/pg/sql/enums.sql
schemainspect_idempotent/pg/sql/extensions.sql
schemainspect_idempotent/pg/sql/functions.sql
schemainspect_idempotent/pg/sql/indexes.sql
schemainspect_idempotent/pg/sql/privileges.sql
schemainspect_idempotent/pg/sql/relations.sql
schemainspect_idempotent/pg/sql/relations9.sql
schemainspect_idempotent/pg/sql/rlspolicies.sql
schemainspect_idempotent/pg/sql/schemas.sql
schemainspect_idempotent/pg/sql/sequences.sql
schemainspect_idempotent/pg/sql/triggers.sql
schemainspect_idempotent/pg/sql/types.sql
schemainspect_idempotent/tableformat.py
schemainspect_idempotent-0.6.dist-info/entry_points.txt
schemainspect_idempotent-0.6.dist-info/LICENSE
schemainspect_idempotent-0.6.dist-info/WHEEL
schemainspect_idempotent-0.6.dist-info/METADATA
schemainspect_idempotent-0.6.dist-info/RECORD
