Metadata-Version: 2.1
Name: schemainspect-idempotent
Version: 0.6
Summary: Schema inspection for PostgreSQL (and possibly others)
Home-page: https://github.com/kahuang/schemainspect
License: Unlicense
Author: Andrew Huang
Author-email: k.andrew.huang@gmail.com
Classifier: License :: Other/Proprietary License
Classifier: Programming Language :: Python :: 2
Classifier: Programming Language :: Python :: 2.7
Classifier: Programming Language :: Python :: 3
Classifier: Programming Language :: Python :: 3.4
Classifier: Programming Language :: Python :: 3.5
Classifier: Programming Language :: Python :: 3.6
Classifier: Programming Language :: Python :: 3.7
Classifier: Programming Language :: Python :: 3.8
Classifier: Programming Language :: Python :: 3.9
Requires-Dist: six
Requires-Dist: sqlalchemy
Project-URL: Repository, https://github.com/kahuang/schemainspect
